minidevtools/__init__.py
minidevtools/cli.py
minidevtools/hash_tool.py
minidevtools/utils/__init__.py
minidevtools/utils/banner.py
minidevtools/utils/check_update.py
minidevtools/utils/config.py
minidevtools/utils/terminalsize.py
minidevtools-0.0.1.dist-info/entry_points.txt
minidevtools-0.0.1.dist-info/LICENSE
minidevtools-0.0.1.dist-info/METADATA
minidevtools-0.0.1.dist-info/WHEEL
minidevtools-0.0.1.dist-info/RECORD
