Metadata-Version: 2.1
Name: minidevtools
Version: 0.0.1
Summary: A Swiss Army knife for developers
Home-page: https://github.com/odest/MiniDevTools
Keywords: Developers,Tools
Author: odest
Author-email: destrochloridium@gmail.com
Maintainer: odest
Maintainer-email: destrochloridium@gmail.com
Requires-Python: >=3.8,<4.0
Classifier: Development Status :: 2 - Pre-Alpha
Classifier: Environment :: Console
Classifier: Intended Audience :: Developers
Classifier: Intended Audience :: Education
Classifier: License :: OSI Approved :: GNU General Public License v3 (GPLv3)
Classifier: Operating System :: OS Independent
Classifier: Programming Language :: Python
Classifier: Programming Language :: Python :: 3
Classifier: Programming Language :: Python :: 3.8
Classifier: Programming Language :: Python :: 3.9
Classifier: Programming Language :: Python :: 3.10
Classifier: Programming Language :: Python :: 3.11
Classifier: Programming Language :: Python :: 3.12
Classifier: Topic :: Software Development :: Libraries :: Python Modules
Requires-Dist: packaging (>=24.0,<25.0)
Requires-Dist: requests (>=2.31.0,<3.0.0)
Requires-Dist: typer (>=0.9.0,<0.10.0)
Requires-Dist: typing_extensions (>=4.10.0,<5.0.0)
Project-URL: Bug Tracker, https://github.com/odest/MiniDevTools/issues
Project-URL: Changelog, https://github.com/odest/MiniDevTools/releases
Project-URL: Documentation, https://minidevtools.readthedocs.io/en/latest/
Project-URL: Source, https://github.com/odest/MiniDevTools
